NaMAZU/__init__.py
NaMAZU/functional/__init__.py
NaMAZU/functional/coreml_control.py
NaMAZU/functional/data_science.py
NaMAZU/functional/file_control.py
NaMAZU/functional/image_control.py
NaMAZU/functional/text_control.py
NaMAZU/lightning_wingman/__init__.py
NaMAZU/lightning_wingman/ani_label.py
NaMAZU/lightning_wingman/aninet.py
NaMAZU/lightning_wingman/inference_helper.py
NaMAZU/lightning_wingman/instance.py
NaMAZU/lightning_wingman/lit_aninet.py
NaMAZU/lightning_wingman/lit_multimodal.py
NaMAZU/lightning_wingman/lit_u2net.py
NaMAZU/lightning_wingman/lit_video_clf.py
NaMAZU/lightning_wingman/multi_modal.py
NaMAZU/lightning_wingman/pretrainer.py
NaMAZU/lightning_wingman/torch_gmm.py
NaMAZU/lightning_wingman/torch_knn.py
NaMAZU/lightning_wingman/torch_nbc.py
NaMAZU/lightning_wingman/u2net.py
NaMAZU/lightning_wingman/video_clf.py
NaMAZU/namadeco/__init__.py
NaMAZU/namadeco/decorations.py
NaMAZU/onnx_api/__init__.py
NaMAZU/onnx_api/midas.py
NaMAZU/onnx_api/real_esr.py
NaMAZU/onnx_api/segmentation.py
NaMAZU/onnx_api/utils.py
NaMAZU/st_integration/__init__.py
NaMAZU/st_integration/clf_template.py
NaMAZU/st_integration/st_utils.py
NaMAZU-0.0.73.dist-info/LICENSE
NaMAZU-0.0.73.dist-info/METADATA
NaMAZU-0.0.73.dist-info/WHEEL
NaMAZU-0.0.73.dist-info/top_level.txt
NaMAZU-0.0.73.dist-info/RECORD
