Metadata-Version: 2.1
Name: NaMAZU
Version: 0.0.73
Summary: NaMAZU: Pretty Usefull Library
Home-page: https://github.com/NMZ0429/NaMAZU
Author: NaMAZU Team
Author-email: bunbun@icloud.com
Maintainer: NaMAZU Team
Maintainer-email: bunbun@icloud.com
License: MIT
Download-URL: https://github.com/NMZ0429/NaMAZU
Platform: UNKNOWN
Classifier: Environment :: Console
Classifier: Natural Language :: English
Classifier: Development Status :: 4 - Beta
Classifier: Intended Audience :: Developers
Classifier: Topic :: Scientific/Engineering :: Artificial Intelligence
Classifier: Topic :: Scientific/Engineering :: Image Recognition
Classifier: Topic :: Scientific/Engineering :: Information Analysis
Classifier: License :: OSI Approved :: Apache Software License
Classifier: Operating System :: OS Independent
Classifier: Programming Language :: Python :: 3
Classifier: Programming Language :: Python :: 3.7
Classifier: Programming Language :: Python :: 3.8
Classifier: Programming Language :: Python :: 3.9
Requires-Python: >=3.7.0
License-File: LICENSE
Requires-Dist: pillow
Requires-Dist: opencv-python
Requires-Dist: scikit-image
Requires-Dist: scikit-learn
Requires-Dist: numpy
Requires-Dist: pandas
Requires-Dist: timm
Requires-Dist: torchvision
Requires-Dist: pytorch-lightning
Requires-Dist: byol-pytorch
Requires-Dist: plotly
Requires-Dist: streamlit
Requires-Dist: onnxruntime
